rustyms-0.10.0.dist-info/METADATA
rustyms-0.10.0.dist-info/WHEEL
rustyms/__init__.py
rustyms/rustyms.cpython-312-darwin.so
rustyms-0.10.0.dist-info/RECORD
