Metadata-Version: 2.4
Name: rustyms
Version: 0.10.0
Classifier: Intended Audience :: Science/Research
Classifier: Programming Language :: Rust
Classifier: Programming Language :: Python :: 3 :: Only
Classifier: Programming Language :: Python :: Implementation :: CPython
Classifier: Topic :: Scientific/Engineering :: Bio-Informatics
Requires-Dist: maturin ; extra == 'dev'
Requires-Dist: sphinx ; extra == 'docs'
Requires-Dist: numpydoc>=1,<2 ; extra == 'docs'
Requires-Dist: myst-parser ; extra == 'docs'
Requires-Dist: sphinx-rtd-theme ; extra == 'docs'
Requires-Dist: sphinx-autobuild ; extra == 'docs'
Requires-Dist: sphinx-automodapi ; extra == 'docs'
Provides-Extra: dev
Provides-Extra: docs
Summary: A library to handle proteomic mass spectrometry data and match peptides to spectra.
License: MIT OR Apache-2.0
Requires-Python: >=3.9, <3.14
Project-URL: Homepage, https://github.com/snijderlab/rustyms
Project-URL: Documentation, https://rustyms.readthedocs.io/
Project-URL: Repository, https://github.com/snijderlab/rustyms.git
